{
    "paths": [
        {
            "name": "/topics",
            "lambdaFunction": "topicsLambda",
            "privacy": {
                "protected": true,
                "auth": [
                    "/POST",
                    "/GET",
                    "/PUT",
                    "/PATCH",
                    "/DELETE"
                ],
                "unauth": [
                    "/GET"
                ]
            },
            "policyResourceName": "/topics"
        },
        {
            "name": "/posts",
            "lambdaFunction": "postsLambda",
            "privacy": {
                "protected": true,
                "auth": [
                    "/POST",
                    "/GET",
                    "/PUT",
                    "/PATCH",
                    "/DELETE"
                ],
                "unauth": [
                    "/GET"
                ]
            },
            "policyResourceName": "/posts"
        },
        {
            "name": "/comments",
            "lambdaFunction": "commentsLambda",
            "privacy": {
                "private": true,
                "auth": [
                    "/POST",
                    "/GET",
                    "/PUT",
                    "/PATCH",
                    "/DELETE"
                ]
            },
            "policyResourceName": "/comments"
        },
        {
            "name": "/topicTest",
            "lambdaFunction": "topicTestsLambda",
            "privacy": {
                "private": true,
                "auth": [
                    "/POST",
                    "/GET",
                    "/PUT",
                    "/PATCH",
                    "/DELETE"
                ]
            },
            "policyResourceName": "/topicTest"
        },
        {
            "name": "/conversations",
            "lambdaFunction": "conversationsLambda",
            "privacy": {
                "private": true,
                "auth": [
                    "/POST",
                    "/GET"
                ]
            },
            "policyResourceName": "/conversations"
        },
        {
            "name": "/profile",
            "lambdaFunction": "profileLambda",
            "privacy": {
                "private": true,
                "auth": [
                    "/POST",
                    "/GET",
                    "/PUT",
                    "/PATCH",
                    "/DELETE"
                ]
            },
            "policyResourceName": "/profile"
        },
        {
            "name": "/timeline",
            "lambdaFunction": "timelineLambda",
            "privacy": {
                "private": true,
                "auth": [
                    "/GET",
                    "/PUT",
                    "/PATCH"
                ]
            },
            "policyResourceName": "/timeline"
        }
    ],
    "resourceName": "topicsApi",
    "apiName": "topicsApi",
    "functionArns": [
        {
            "lambdaFunction": "topicsLambda"
        },
        {
            "lambdaFunction": "postsLambda"
        },
        {
            "lambdaFunction": "commentsLambda"
        },
        {
            "lambdaFunction": "topicTestsLambda"
        },
        {
            "lambdaFunction": "conversationsLambda"
        },
        {
            "lambdaFunction": "profileLambda"
        },
        {
            "lambdaFunction": "timelineLambda"
        }
    ],
    "privacy": {
        "auth": 7,
        "unauth": 2,
        "authRoleName": "amplify-socialmedia-dev-131342-authRole",
        "unAuthRoleName": "amplify-socialmedia-dev-131342-unauthRole"
    },
    "dependsOn": [
        {
            "category": "function",
            "resourceName": "topicsLambda",
            "attributes": [
                "Name",
                "Arn"
            ]
        },
        {
            "category": "function",
            "resourceName": "postsLambda",
            "attributes": [
                "Name",
                "Arn"
            ]
        },
        {
            "category": "function",
            "resourceName": "commentsLambda",
            "attributes": [
                "Name",
                "Arn"
            ]
        },
        {
            "category": "function",
            "resourceName": "topicTestsLambda",
            "attributes": [
                "Name",
                "Arn"
            ]
        },
        {
            "category": "function",
            "resourceName": "conversationsLambda",
            "attributes": [
                "Name",
                "Arn"
            ]
        },
        {
            "category": "function",
            "resourceName": "profileLambda",
            "attributes": [
                "Name",
                "Arn"
            ]
        },
        {
            "category": "function",
            "resourceName": "timelineLambda",
            "attributes": [
                "Name",
                "Arn"
            ]
        }
    ],
    "uuid": "2cbb81ae"
}